[{"name": "AniLifeSchedule", "url": "https://github.com/DiamondKesha/AniLifeSchedule", "description": "Application for generation anime schedule based on Blazor Server and created for my own group AniLife", "language": ["C#", "HTML", "CSS"], "forks_count": 0, "stargazers_count": 0, "watchers_count": 0, "size": 275, "topics": []}, {"name": "DiamondKesha", "url": "https://github.com/DiamondKesha/DiamondKesha", "description": "Config files for my GitHub profile.", "language": [], "forks_count": 0, "stargazers_count": 0, "watchers_count": 0, "size": 0, "topics": ["config", "github-config"]}, {"name": "The-Documentation-Compendium", "url": "https://github.com/DiamondKesha/The-Documentation-Compendium", "description": "\ud83d\udce2 Various README templates & tips on writing high-quality documentation that people want to read.", "language": [], "forks_count": 0, "stargazers_count": 0, "watchers_count": 0, "size": 178, "topics": []}]