[{"name": "batchrenorm", "url": "https://github.com/jjaskirat/batchrenorm", "description": "Batch Renormalization in Pytorch", "language": ["Python"], "forks_count": 0, "stargazers_count": 0, "watchers_count": 0, "size": 14, "topics": []}, {"name": "Blockchain", "url": "https://github.com/jjaskirat/Blockchain", "description": null, "language": ["Python"], "forks_count": 0, "stargazers_count": 0, "watchers_count": 0, "size": 175, "topics": []}, {"name": "BlockChain-Authenticator-Disease-Predictor-Recommender-System", "url": "https://github.com/jjaskirat/BlockChain-Authenticator-Disease-Predictor-Recommender-System", "description": null, "language": ["Python", "HTML", "CSS"], "forks_count": 0, "stargazers_count": 0, "watchers_count": 0, "size": 23340, "topics": []}, {"name": "certificates", "url": "https://github.com/jjaskirat/certificates", "description": null, "language": [], "forks_count": 0, "stargazers_count": 0, "watchers_count": 0, "size": 1122, "topics": []}, {"name": "code_snippets", "url": "https://github.com/jjaskirat/code_snippets", "description": null, "language": ["Python", "HTML", "CSS", "Shell", "JavaScript", "Batchfile"], "forks_count": 0, "stargazers_count": 0, "watchers_count": 0, "size": 3254, "topics": []}, {"name": "CS886", "url": "https://github.com/jjaskirat/CS886", "description": "Causal Inference in Machine Learning", "language": ["TeX"], "forks_count": 0, "stargazers_count": 0, "watchers_count": 0, "size": 94, "topics": []}, {"name": "Customer-Complaint-Analyzer", "url": "https://github.com/jjaskirat/Customer-Complaint-Analyzer", "description": "project", "language": ["Scala"], "forks_count": 0, "stargazers_count": 0, "watchers_count": 0, "size": 300, "topics": []}, {"name": "Disease-Predictor", "url": "https://github.com/jjaskirat/Disease-Predictor", "description": null, "language": [], "forks_count": 0, "stargazers_count": 0, "watchers_count": 0, "size": 3, "topics": []}, {"name": "Drug-Target-Interaction", "url": "https://github.com/jjaskirat/Drug-Target-Interaction", "description": null, "language": ["Python", "HTML", "CSS"], "forks_count": 0, "stargazers_count": 0, "watchers_count": 0, "size": 42093, "topics": []}, {"name": "EM-Algorithm", "url": "https://github.com/jjaskirat/EM-Algorithm", "description": null, "language": [], "forks_count": 0, "stargazers_count": 0, "watchers_count": 0, "size": 6, "topics": []}, {"name": "extend-ai-ml-assessment", "url": "https://github.com/jjaskirat/extend-ai-ml-assessment", "description": null, "language": ["Jupyter Notebook"], "forks_count": 0, "stargazers_count": 0, "watchers_count": 0, "size": 78798, "topics": []}, {"name": "Gibbs-Sampler", "url": "https://github.com/jjaskirat/Gibbs-Sampler", "description": null, "language": [], "forks_count": 0, "stargazers_count": 0, "watchers_count": 0, "size": 4, "topics": []}, {"name": "jjaskirat.github.io", "url": "https://github.com/jjaskirat/jjaskirat.github.io", "description": null, "language": ["SCSS", "CSS", "JavaScript", "HTML"], "forks_count": 0, "stargazers_count": 0, "watchers_count": 0, "size": 1517, "topics": []}, {"name": "MixNMatch", "url": "https://github.com/jjaskirat/MixNMatch", "description": "Pytorch implementation of MixNMatch", "language": ["Python"], "forks_count": 0, "stargazers_count": 0, "watchers_count": 0, "size": 21172, "topics": []}, {"name": "ML-From-Scratch", "url": "https://github.com/jjaskirat/ML-From-Scratch", "description": null, "language": ["Jupyter Notebook"], "forks_count": 0, "stargazers_count": 0, "watchers_count": 0, "size": 401, "topics": []}, {"name": "Multi-Task-Learning-PyTorch", "url": "https://github.com/jjaskirat/Multi-Task-Learning-PyTorch", "description": "PyTorch implementation of multi-task learning architectures, incl. MTI-Net (ECCV2020).", "language": ["Python", "MATLAB"], "forks_count": 0, "stargazers_count": 0, "watchers_count": 0, "size": 79364, "topics": []}, {"name": "Predicting-Life-Satisfaction", "url": "https://github.com/jjaskirat/Predicting-Life-Satisfaction", "description": null, "language": ["R"], "forks_count": 0, "stargazers_count": 0, "watchers_count": 0, "size": 0, "topics": []}, {"name": "Reports", "url": "https://github.com/jjaskirat/Reports", "description": null, "language": [], "forks_count": 0, "stargazers_count": 0, "watchers_count": 0, "size": 7634, "topics": []}, {"name": "segmentation_models.pytorch", "url": "https://github.com/jjaskirat/segmentation_models.pytorch", "description": "Segmentation models with pretrained backbones. PyTorch.", "language": ["Python", "Dockerfile"], "forks_count": 0, "stargazers_count": 0, "watchers_count": 0, "size": 4991, "topics": []}, {"name": "Sentiment-Analyzer-and-Email-Classifier", "url": "https://github.com/jjaskirat/Sentiment-Analyzer-and-Email-Classifier", "description": null, "language": ["Jupyter Notebook"], "forks_count": 0, "stargazers_count": 0, "watchers_count": 0, "size": 6, "topics": []}, {"name": "Street-Sign-Classification", "url": "https://github.com/jjaskirat/Street-Sign-Classification", "description": null, "language": ["Jupyter Notebook"], "forks_count": 0, "stargazers_count": 0, "watchers_count": 0, "size": 37814, "topics": []}, {"name": "Swin-Transformer", "url": "https://github.com/jjaskirat/Swin-Transformer", "description": "This is an official implementation for \"Swin Transformer: Hierarchical Vision Transformer using Shifted Windows\".", "language": ["Python"], "forks_count": 0, "stargazers_count": 0, "watchers_count": 0, "size": 937, "topics": []}]