[{"name": "adversarial-robustness-toolbox", "url": "https://github.com/PetrovKP/adversarial-robustness-toolbox", "description": "Adversarial Robustness Toolbox (ART) - Python Library for Machine Learning Security - Evasion, Poisoning, Extraction, Inference - Red and Blue Teams", "language": ["Python", "Shell", "Dockerfile", "Makefile"], "forks_count": 0, "stargazers_count": 0, "watchers_count": 0, "size": 196708, "topics": []}, {"name": "analytics-zoo", "url": "https://github.com/PetrovKP/analytics-zoo", "description": "Distributed Tensorflow, Keras and PyTorch on Apache Spark/Flink & Ray", "language": ["Jupyter Notebook", "Python", "Scala", "Shell", "Dockerfile", "Java", "RobotFramework", "Makefile", "Groovy", "PureBasic"], "forks_count": 0, "stargazers_count": 0, "watchers_count": 0, "size": 230459, "topics": []}, {"name": "autogluon", "url": "https://github.com/PetrovKP/autogluon", "description": "AutoGluon: AutoML for Text, Image, and Tabular Data", "language": ["Python", "Shell"], "forks_count": 0, "stargazers_count": 0, "watchers_count": 0, "size": 9348, "topics": []}, {"name": "awesome-machine-learning", "url": "https://github.com/PetrovKP/awesome-machine-learning", "description": "A curated list of awesome Machine Learning frameworks, libraries and software.", "language": ["Python"], "forks_count": 0, "stargazers_count": 0, "watchers_count": 0, "size": 2249, "topics": []}, {"name": "awesome-python", "url": "https://github.com/PetrovKP/awesome-python", "description": "A curated list of awesome Python frameworks, libraries, software and resources", "language": ["Python", "Makefile"], "forks_count": 0, "stargazers_count": 0, "watchers_count": 0, "size": 6613, "topics": []}, {"name": "computecpp-sdk", "url": "https://github.com/PetrovKP/computecpp-sdk", "description": "Collection of samples and utilities for using ComputeCpp, Codeplay's SYCL implementation", "language": ["C++", "CMake", "Python", "Cuda", "Makefile", "Shell"], "forks_count": 0, "stargazers_count": 0, "watchers_count": 0, "size": 1071, "topics": []}, {"name": "courses", "url": "https://github.com/PetrovKP/courses", "description": null, "language": ["Jupyter Notebook", "C++", "CMake", "Python", "C", "GLSL", "PHP", "Cuda", "Shell", "CSS"], "forks_count": 0, "stargazers_count": 0, "watchers_count": 0, "size": 20566, "topics": []}, {"name": "daal", "url": "https://github.com/PetrovKP/daal", "description": "Intel\u00ae Data Analytics Acceleration Library (Intel\u00ae DAAL) ", "language": ["C++", "Java", "SWIG", "C", "Starlark", "Makefile", "Shell", "Python", "Batchfile", "CMake", "Smarty"], "forks_count": 0, "stargazers_count": 0, "watchers_count": 0, "size": 167798, "topics": []}, {"name": "daal4py", "url": "https://github.com/PetrovKP/daal4py", "description": "sources for daal4py - a convenient Python API to DAAL", "language": ["Python", "C++", "Shell", "CMake", "C", "Batchfile"], "forks_count": 0, "stargazers_count": 0, "watchers_count": 0, "size": 43173, "topics": []}, {"name": "daal4py-feedstock", "url": "https://github.com/PetrovKP/daal4py-feedstock", "description": "A conda-smithy repository for daal4py.", "language": ["Shell", "Batchfile"], "forks_count": 0, "stargazers_count": 0, "watchers_count": 0, "size": 103, "topics": []}, {"name": "daal4py-test-pypi", "url": "https://github.com/PetrovKP/daal4py-test-pypi", "description": null, "language": [], "forks_count": 2, "stargazers_count": 0, "watchers_count": 0, "size": 197340, "topics": []}, {"name": "deeplearningcourse", "url": "https://github.com/PetrovKP/deeplearningcourse", "description": null, "language": ["Jupyter Notebook"], "forks_count": 0, "stargazers_count": 0, "watchers_count": 0, "size": 9941, "topics": []}, {"name": "deep_learning", "url": "https://github.com/PetrovKP/deep_learning", "description": null, "language": ["Jupyter Notebook", "Python"], "forks_count": 0, "stargazers_count": 0, "watchers_count": 0, "size": 45, "topics": []}, {"name": "facial-expression-recognition-svm", "url": "https://github.com/PetrovKP/facial-expression-recognition-svm", "description": "Training SVM classifier to recognize people expressions (emotions) on Fer2013 dataset", "language": ["Python"], "forks_count": 0, "stargazers_count": 0, "watchers_count": 0, "size": 4275, "topics": []}, {"name": "fpga-demo", "url": "https://github.com/PetrovKP/fpga-demo", "description": "Fpga demo for de10-nano", "language": ["C", "Makefile", "Shell"], "forks_count": 0, "stargazers_count": 0, "watchers_count": 0, "size": 8, "topics": []}, {"name": "heat-distribution", "url": "https://github.com/PetrovKP/heat-distribution", "description": "\u0420\u0435\u0448\u0435\u043d\u0438\u0435 \u0437\u0430\u0434\u0430\u0447\u0438 \u0440\u0430\u0441\u043f\u0440\u0435\u0434\u0435\u043b\u0435\u043d\u0438\u044f \u0442\u0435\u043f\u043b\u0430 \u0432 \u0441\u0442\u0435\u0440\u0436\u043d\u0435 \u0440\u0430\u0437\u043b\u0438\u0447\u043d\u044b\u043c\u0438 \u0441\u043f\u043e\u0441\u043e\u0431\u0430\u043c\u0438 \u0438 \u043c\u0435\u0442\u043e\u0434\u0430\u043c\u0438. \u0412\u0438\u0437\u0443\u0430\u043b\u0438\u0437\u0430\u0446\u0438\u044f \u0438 \u0430\u043d\u0430\u043b\u0438\u0437\u0438\u0440\u043e\u0432\u0430\u043d\u0438\u0435 \u043f\u043e\u043b\u0443\u0447\u0435\u043d\u043d\u044b\u0445 \u0434\u0430\u043d\u043d\u044b\u0445.", "language": ["C", "C++", "Python", "CMake", "Shell"], "forks_count": 0, "stargazers_count": 0, "watchers_count": 0, "size": 5359, "topics": []}, {"name": "heat-equation", "url": "https://github.com/PetrovKP/heat-equation", "description": "\u0423\u0440\u0430\u0432\u043d\u0435\u043d\u0438\u0435 \u0442\u0435\u043f\u043b\u043e\u043f\u0440\u043e\u0432\u043e\u0434\u043d\u043e\u0441\u0442\u0438 \u0432 \u0442\u0440\u0451\u0445\u043c\u0435\u0440\u0435", "language": ["C", "C++", "CMake", "Python", "Shell"], "forks_count": 0, "stargazers_count": 0, "watchers_count": 0, "size": 31526, "topics": ["avx2", "fpga", "heat-equation", "mkl", "mpi", "opencl", "openmp"]}, {"name": "intel_repack-feedstock", "url": "https://github.com/PetrovKP/intel_repack-feedstock", "description": "A conda-smithy repository for intel_repack.", "language": ["Shell", "Batchfile"], "forks_count": 0, "stargazers_count": 0, "watchers_count": 0, "size": 127, "topics": []}, {"name": "oneAPI-samples", "url": "https://github.com/PetrovKP/oneAPI-samples", "description": "Samples for Intel oneAPI toolkits", "language": ["HTML", "C++", "C", "Jupyter Notebook", "CMake", "Python", "Shell", "Makefile", "Fortran", "Cuda", "Verilog"], "forks_count": 0, "stargazers_count": 0, "watchers_count": 0, "size": 126714, "topics": []}, {"name": "PetrovKP", "url": "https://github.com/PetrovKP/PetrovKP", "description": "My personal repository.", "language": [], "forks_count": 1, "stargazers_count": 0, "watchers_count": 0, "size": 88, "topics": []}, {"name": "project-management-system", "url": "https://github.com/PetrovKP/project-management-system", "description": "\u0421\u0438\u0441\u0442\u0435\u043c\u0430 \u0443\u043f\u0440\u0430\u0432\u043b\u0435\u043d\u0438\u044f \u043f\u0440\u043e\u0435\u043a\u0442\u0430\u043c\u0438", "language": ["Python", "HTML"], "forks_count": 0, "stargazers_count": 0, "watchers_count": 0, "size": 102, "topics": []}, {"name": "pseudo-git", "url": "https://github.com/PetrovKP/pseudo-git", "description": null, "language": ["Java", "Shell"], "forks_count": 0, "stargazers_count": 0, "watchers_count": 0, "size": 162, "topics": []}, {"name": "sbermarket-api", "url": "https://github.com/PetrovKP/sbermarket-api", "description": "api \u043a\u043b\u0438\u0435\u043d\u0442 \u0434\u043b\u044f \u0421\u0431\u0435\u0440\u043c\u0430\u0440\u043a\u0435\u0442", "language": ["TypeScript", "Shell"], "forks_count": 0, "stargazers_count": 0, "watchers_count": 0, "size": 202, "topics": []}, {"name": "scikit-learn-intelex-feedstock", "url": "https://github.com/PetrovKP/scikit-learn-intelex-feedstock", "description": "A conda-smithy repository for scikit-learn-intelex.", "language": [], "forks_count": 0, "stargazers_count": 0, "watchers_count": 0, "size": 34, "topics": []}, {"name": "scikit-learn_bench", "url": "https://github.com/PetrovKP/scikit-learn_bench", "description": "Benchmark for optimizations to scikit-learn in the Intel Distribution for Python*", "language": ["C++", "Python", "Fortran", "Makefile", "C"], "forks_count": 1, "stargazers_count": 0, "watchers_count": 0, "size": 851, "topics": []}, {"name": "svm_benchmarks", "url": "https://github.com/PetrovKP/svm_benchmarks", "description": null, "language": ["Python"], "forks_count": 4, "stargazers_count": 0, "watchers_count": 0, "size": 41, "topics": []}, {"name": "test-suites", "url": "https://github.com/PetrovKP/test-suites", "description": "\u0412\u0435\u0431-\u043f\u0440\u0438\u043b\u043e\u0436\u0435\u043d\u0438\u0435,  \u043e\u0442\u043e\u0431\u0440\u0430\u0436\u0430\u044e\u0449\u0435\u0435 \u0441\u043f\u0438\u0441\u043e\u043a test suites \u0438 \u0443\u043c\u0435\u044e\u0449\u0435\u0435 \u0437\u0430\u043f\u0443\u0441\u043a\u0430\u0442\u044c \u0438\u0445", "language": ["Python", "HTML"], "forks_count": 1, "stargazers_count": 0, "watchers_count": 0, "size": 78, "topics": []}]